{
  "images": {
    "base-images": [
      {
        "date": "2019-05-15",
        "description": "Cloudbreak image",
        "images": {
          "aws": {
            "eu-west-1": "ami-09fe52c3d346ba0d8"
          }
        },
        "os": "amazonlinux",
        "os_type": "redhat6",
        "uuid": "50397593-14d3-474b-46b5-020f5aeaaeb4"
      }
    ]
  },
  "versions": {
    "cloudbreak": [
      {
        "images": [
          "50397593-14d3-474b-46b5-020f5aeaaeb4"
        ],
        "defaults": [
          "50397593-14d3-474b-46b5-020f5aeaaeb4"
        ],
        "versions": [
          "2.9.0"
        ]
      },
      {
        "images": [
          "50397593-14d3-474b-46b5-020f5aeaaeb4"
        ],
        "defaults": [
          "50397593-14d3-474b-46b5-020f5aeaaeb4"
        ],
        "versions": [
          "2.9.0"
        ]
      }
    ]
  }
}
